cumulusci_ado/__about__.py
cumulusci_ado/__init__.py
cumulusci_ado/azure_devops.py
cumulusci_ado/cumulusci_plugin.yml
cumulusci_ado/cli/__init__.py
cumulusci_ado/cli/ado.py
cumulusci_ado/utils/ado.py
cumulusci_ado/utils/common/artifacttool.py
cumulusci_ado/utils/common/artifacttool_updater.py
cumulusci_ado/utils/common/external_tool.py
cumulusci_ado/utils/common/client_tool/__init__.py
cumulusci_ado/utils/common/client_tool/client_tool_client.py
cumulusci_ado/utils/common/client_tool/models/__init__.py
cumulusci_ado/utils/common/client_tool/models/client_tool_release.py
cumulusci_ado/utils/common/tests/test_artifacttool_updater.py
cumulusci_ado/utils/tests/test_ado.py
cumulusci_ado/vcs/ado/__init__.py
cumulusci_ado/vcs/ado/adapter.py
cumulusci_ado/vcs/ado/exceptions.py
cumulusci_ado/vcs/ado/service.py
cumulusci_ado/vcs/ado/dependencies/__init__.py
cumulusci_ado/vcs/ado/dependencies/ado_dependencies.py
cumulusci_ado/vcs/ado/dependencies/ado_resolvers.py
cumulusci_ado/vcs/ado/generator/__init__.py
cumulusci_ado/vcs/ado/source/azure_devops.py
cumulusci_ado/vcs/ado/tests/test_adapter.py
cumulusci_ado/vcs/ado/tests/test_service.py
cumulusci_plus_azure_devops-0.0.11.dist-info/METADATA
cumulusci_plus_azure_devops-0.0.11.dist-info/WHEEL
cumulusci_plus_azure_devops-0.0.11.dist-info/entry_points.txt
cumulusci_plus_azure_devops-0.0.11.dist-info/licenses/LICENSE
cumulusci_plus_azure_devops-0.0.11.dist-info/RECORD
