Metadata-Version: 2.4
Name: cumulusci-plus-azure-devops
Version: 0.0.11
Summary: A plugin for cumulusci plus supporting Azure DevOps
Project-URL: Homepage, https://github.com/jorgesolebur/CumulusCI_AzureDevOps
Project-URL: Bug Tracker, https://github.com/jorgesolebur/CumulusCI_AzureDevOps/issues
Author: Rupesh J
License: GNU General Public License v3.0
License-File: LICENSE
Keywords: azure devops,cumulusci,salesforce
Classifier: Development Status :: 3 - Alpha
Classifier: Intended Audience :: Developers
Classifier: License :: OSI Approved :: GNU General Public License v3 (GPLv3)
Classifier: Programming Language :: Python :: 3.11
Classifier: Programming Language :: Python :: 3.12
Classifier: Topic :: Software Development :: Build Tools
Requires-Python: >=3.11
Requires-Dist: azure-devops
Requires-Dist: cumulusci-plus>=5.0.32
Requires-Dist: distro
Requires-Dist: humanfriendly
Requires-Dist: packaging>=23.0
Requires-Dist: requests
Provides-Extra: dev
Requires-Dist: coverage; extra == 'dev'
Requires-Dist: factory-boy; extra == 'dev'
Requires-Dist: pytest; extra == 'dev'
Requires-Dist: pytest-cov; extra == 'dev'
Requires-Dist: responses; extra == 'dev'
Provides-Extra: docs
Requires-Dist: myst-parser; extra == 'docs'
Requires-Dist: sphinx; extra == 'docs'
Provides-Extra: lint
Requires-Dist: black; extra == 'lint'
Requires-Dist: flake8; extra == 'lint'
Requires-Dist: isort; extra == 'lint'
Requires-Dist: pre-commit; extra == 'lint'
